nyz_dynamic_design_builder/__init__.py
nyz_dynamic_design_builder/builder.py
nyz_dynamic_design_builder-3.0.1.dist-info/licenses/LICENSE
nyz_dynamic_design_builder-3.0.1.dist-info/METADATA
nyz_dynamic_design_builder-3.0.1.dist-info/WHEEL
nyz_dynamic_design_builder-3.0.1.dist-info/top_level.txt
nyz_dynamic_design_builder-3.0.1.dist-info/RECORD
