Metadata-Version: 2.4
Name: nyz-dynamic-design-builder
Version: 3.0.1
Summary: Dynamic Excel export builder for Django ORM querysets
Home-page: https://github.com/niyaziozydn/nyz-dynamic-design-builder
Author: Niyazi Özaydın
Author-email: Niyazi Özaydın <niyazi.ozydn@gmail.com>
License: MIT License
Requires-Python: >=3.10
License-File: LICENSE
Requires-Dist: pandas>=2.2.3
Requires-Dist: django>=5.1.4
Dynamic: author
Dynamic: home-page
Dynamic: license-file
Dynamic: requires-python
